MANIFEST.in
README.md
setup.py
rockchisel/__init__.py
rockchisel/builder.py
rockchisel.egg-info/PKG-INFO
rockchisel.egg-info/SOURCES.txt
rockchisel.egg-info/dependency_links.txt
rockchisel.egg-info/top_level.txt
rockchisel/snippets/__init__.py
rockchisel/snippets/macros.j2
rockchisel/snippets/user_macros.j2
rockchisel/themes/__init__.py
rockchisel/themes/rockdoc/__init__.py
rockchisel/themes/rockdoc/footer.j2
rockchisel/themes/rockdoc/header.j2
rockchisel/themes/rockdoc/rockdoc.css
rockchisel/themes/rockdoc/theme.j2
rockchisel/themes/rockdoc/topleft.j2